CHANGELOG.md
LICENSE
MANIFEST.in
Makefile.am
Makefile.in
README.md
aclocal.m4
compile
config.guess
config.h
config.h.in
config.sub
configure
configure.ac
depcomp
fly.conf
install-sh
libtool
ltmain.sh
missing
requirements.txt
setup.cfg
setup.py
fly/__init__.py
fly/__init__.py.in
fly/__init__.pyc
fly/__main__.py
fly/_base.py
fly/_parse.py
fly/app.py
fly/cookie.py
fly/cors.py
fly/err.py
fly/exceptions.py
fly/helper.py
fly/main.py
fly/method.py
fly/mount.py
fly/response.py
fly/route.py
fly/template.py
fly/types.py
fly/__pycache__/__init__.cpython-310.pyc
fly/__pycache__/__init__.cpython-38.pyc
fly/__pycache__/__main__.cpython-310.pyc
fly/__pycache__/__main__.cpython-38.pyc
fly/__pycache__/_base.cpython-310.pyc
fly/__pycache__/_base.cpython-38.pyc
fly/__pycache__/_parse.cpython-310.pyc
fly/__pycache__/_parse.cpython-38.pyc
fly/__pycache__/app.cpython-310.pyc
fly/__pycache__/app.cpython-38.pyc
fly/__pycache__/cookie.cpython-310.pyc
fly/__pycache__/cookie.cpython-38.pyc
fly/__pycache__/cors.cpython-38.pyc
fly/__pycache__/err.cpython-38.pyc
fly/__pycache__/exceptions.cpython-310.pyc
fly/__pycache__/exceptions.cpython-38.pyc
fly/__pycache__/helper.cpython-310.pyc
fly/__pycache__/helper.cpython-38.pyc
fly/__pycache__/main.cpython-310.pyc
fly/__pycache__/main.cpython-38.pyc
fly/__pycache__/method.cpython-310.pyc
fly/__pycache__/method.cpython-38.pyc
fly/__pycache__/mount.cpython-310.pyc
fly/__pycache__/mount.cpython-38.pyc
fly/__pycache__/response.cpython-310.pyc
fly/__pycache__/response.cpython-38.pyc
fly/__pycache__/route.cpython-310.pyc
fly/__pycache__/route.cpython-38.pyc
fly/__pycache__/template.cpython-310.pyc
fly/__pycache__/template.cpython-38.pyc
fly/__pycache__/types.cpython-310.pyc
fly/__pycache__/types.cpython-38.pyc
fly/lib/libfly.so
fly/lib/libfly.so.0
fly/lib/libfly.so.0.0.0
fly_server.egg-info/PKG-INFO
fly_server.egg-info/SOURCES.txt
fly_server.egg-info/dependency_links.txt
fly_server.egg-info/entry_points.txt
fly_server.egg-info/not-zip-safe
fly_server.egg-info/requires.txt
fly_server.egg-info/top_level.txt
m4/libtool.m4
m4/ltoptions.m4
m4/ltsugar.m4
m4/ltversion.m4
m4/lt~obsolete.m4
src/Makefile
src/Makefile.am
src/Makefile.in
src/alloc.c
src/alloc.h
src/bllist.c
src/bllist.h
src/body.c
