Metadata-Version: 2.1
Name: fly-server
Version: 1.4.0
Summary: lightweight web framework
Home-page: https://github.com/tatsuya4649/fly
Author: tatsuya.s
Author-email: tatsuya4946developer@gmail.com
License: UNKNOWN
Keywords: HTTP Web-server app-server
Platform: UNKNOWN
Classifier: License :: OSI Approved :: MIT License
Classifier: Operating System :: POSIX
Classifier: Operating System :: POSIX :: Linux
Classifier: Programming Language :: C
Classifier: Programming Language :: Python
Classifier: Programming Language :: Python :: 3.6
Classifier: Programming Language :: Python :: 3.7
Classifier: Programming Language :: Python :: 3.8
Classifier: Programming Language :: Python :: 3.9
Classifier: Programming Language :: Python :: 3.10
Classifier: Programming Language :: Python :: Implementation :: CPython
Classifier: Topic :: Internet :: WWW/HTTP
Classifier: Topic :: Internet :: WWW/HTTP :: HTTP Servers
Requires-Python: >=3.6
Provides-Extra: test
Provides-Extra: dev
